odoo/addons/partner_email_duplicate_warn/README.rst
odoo/addons/partner_email_duplicate_warn/__init__.py
odoo/addons/partner_email_duplicate_warn/__manifest__.py
odoo/addons/partner_email_duplicate_warn/i18n/partner_email_duplicate_warn.pot
odoo/addons/partner_email_duplicate_warn/models/__init__.py
odoo/addons/partner_email_duplicate_warn/models/res_partner.py
odoo/addons/partner_email_duplicate_warn/readme/CONFIGURE.rst
odoo/addons/partner_email_duplicate_warn/readme/CONTRIBUTORS.rst
odoo/addons/partner_email_duplicate_warn/readme/DESCRIPTION.rst
odoo/addons/partner_email_duplicate_warn/readme/USAGE.rst
odoo/addons/partner_email_duplicate_warn/static/description/icon.png
odoo/addons/partner_email_duplicate_warn/static/description/index.html
odoo/addons/partner_email_duplicate_warn/static/description/partner_warn_banner.png
odoo/addons/partner_email_duplicate_warn/tests/__init__.py
odoo/addons/partner_email_duplicate_warn/tests/test_email_duplicate.py
odoo/addons/partner_email_duplicate_warn/views/res_partner.xml
odoo14_addon_partner_email_duplicate_warn-14.0.1.0.1.dist-info/METADATA
odoo14_addon_partner_email_duplicate_warn-14.0.1.0.1.dist-info/WHEEL
odoo14_addon_partner_email_duplicate_warn-14.0.1.0.1.dist-info/top_level.txt
odoo14_addon_partner_email_duplicate_warn-14.0.1.0.1.dist-info/RECORD
